d3adc0re_tools/PyProxy.py
d3adc0re_tools/SongDownloader.py
d3adc0re_tools/__init__.py
D3adC0re_Tools-0.1.dist-info/METADATA
D3adC0re_Tools-0.1.dist-info/WHEEL
D3adC0re_Tools-0.1.dist-info/top_level.txt
D3adC0re_Tools-0.1.dist-info/RECORD
