Metadata-Version: 2.1
Name: D3adC0re-Tools
Version: 0.1
Summary: D3adC0re Tools
Author: Purpl3
Author-email: d3adc0re@suntimedev.com
License: MIT
Requires-Dist: googlesearch-python
